LICENSE
MANIFEST.in
README.rst
setup.cfg
setup.py
fincoretails/__init__.py
fincoretails/algpareto.py
fincoretails/analysis.py
fincoretails/dists.py
fincoretails/expareto.py
fincoretails/expon.py
fincoretails/general_algpareto.py
fincoretails/general_expareto.py
fincoretails/general_powpareto.py
fincoretails/lognormal.py
fincoretails/metadata.py
fincoretails/powpareto.py
fincoretails/santafe.py
fincoretails/tools.py
fincoretails/unipareto.py
fincoretails.egg-info/PKG-INFO
fincoretails.egg-info/SOURCES.txt
fincoretails.egg-info/dependency_links.txt
fincoretails.egg-info/not-zip-safe
fincoretails.egg-info/requires.txt
fincoretails.egg-info/top_level.txt