Metadata-Version: 2.1
Name: fincoretails
Version: 0.0.0
Summary: Fit a bunch of distributions with finite core and heavy tails to data.
Home-page: https://github.com/benmaier/fincoretails
Author: Benjamin F. Maier
Author-email: contact@benmaier.org
License: MIT
Project-URL: Documentation, http://fincoretails.benmaier.org
Project-URL: Contributing Statement, https://github.com/benmaier/fincoretails/blob/master/CONTRIBUTING.md
Project-URL: Bug Reports, https://github.com/benmaier/fincoretails/issues
Project-URL: Source, https://github.com/benmaier/fincoretails/
Project-URL: PyPI, https://pypi.org/project/fincoretails/
Classifier: License :: OSI Approved :: MIT License
Classifier: Programming Language :: Python :: 3.6
Classifier: Programming Language :: Python :: 3.7
Classifier: Programming Language :: Python :: 3.8
Classifier: Programming Language :: Python :: 3.9
Classifier: Programming Language :: Python :: 3.10
Classifier: Programming Language :: Python :: 3.11
Requires-Python: >=3.6
License-File: LICENSE
